[
  {
    "topic": "Sora 종료 이후 디렉터가 실제 쓰는 AI 영상 모델 4종 비교 (파사드 루프 기준)",
    "image_query": "AI video generation screen dark studio monitor glow",
    "instagram": {
      "caption": "「창작 노트」\n\nSora가 사라졌다.\n2026년 4월, 조용히 문을 닫았다.\n\n그러자 현장에서 쓰는 도구가 다시 보이기 시작했다.\n\n파사드 루프 하나를 기준으로 Veo 3.1, Kling 3.0, Seedance 2.0, Runway를 나란히 돌려봤다.\n결과가 꽤 달랐다.\n\n캐러셀에 정리했으니 저장해두고 참고하세요.\n\n\nSora quietly shut down in April 2026.\nI tested Veo 3.1, Kling 3.0, Seedance 2.0, and Runway side by side on a facade loop.\nThe differences were real.\n\n#AI영상 #생성AI #미디어아트 #파사드 #디렉터노트 #AIcreative #Runway #Kling",
      "series": "AI for Creators"
    },
    "facebook": {
      "text": "「창작 노트」\n\nSora가 없어진 날, 나는 딱히 당황하지 않았다.\n\n2026년 4월, Sora가 서비스를 종료했다. 주변 반응은 둘로 나뉘었다. 아쉬워하는 사람과, 원래 잘 안 쓰고 있었던 사람. 나는 후자였다.\n\n실제로 파사드 루프처럼 반복 재생이 중요한 작업에서 Sora는 루프 연결이 어색했다. 화려한 데모 영상과 실무의 요구 사이에는 늘 간격이 있다.\n\nSora 이후 나는 네 가지 모델을 파사드 루프라는 같은 조건 위에 올려놨다. Veo 3.1, Kling 3.0, Seedance 2.0, Runway.\n\n결과는 제각각이었다. 모션의 자연스러움, 루프 연결의 매끄러움, 프롬프트 반응 속도 — 같은 기준으로 재봤을 때 강점이 겹치는 모델이 없었다. 잘하는 영역이 서로 달랐다.\n\n디렉터 입장에서 중요한 건 '어느 모델이 최고냐'가 아니다. 어떤 장면에, 어떤 조건에, 어느 도구를 꺼낼지 아는 것이다. 도구가 하나일 때보다 여럿일 때 판단이 더 중요해진다.\n\nSora가 닫힌 게 기회였다고 생각한다. 하나에 의존하지 않는 습관을 다시 점검하게 됐으니까.\n\n당신은 지금 쓰는 AI 영상 도구가 사라지면, 바로 다음 선택지가 있나요?"
    },
    "linkedin": {
      "text": "「창작 노트」\n\nSora가 사라진 뒤, 나는 오히려 선택지가 선명해졌다.\n\n2026년 4월 Sora 서비스가 종료됐다. 많은 크리에이터가 당황했지만, 솔직히 파사드 루프처럼 반복 재생이 핵심인 작업에서 Sora는 처음부터 아쉬운 도구였다.\n\n그래서 나는 실제로 현장에서 대안이 되는 네 가지 모델을 같은 조건 위에서 비교해봤다.\nVeo 3.1, Kling 3.0, Seedance 2.0, Runway.\n\n파사드 루프를 기준으로 삼은 이유가 있다.\n루프는 까다롭다. 처음과 끝이 자연스럽게 이어져야 하고, 모션이 반복돼도 피로하지 않아야 한다. 데모 영상에서 잘 보이는 모델이 이 조건에서도 강하다는 보장은 없다.\n\n결과적으로 네 도구의 강점은 겹치지 않았다.\n모션 자연스러움이 뛰어난 모델이 루프 연결에서 약했고, 프롬프트 반응이 빠른 모델이 색감 일관성에서 흔들렸다.\n\n\"도구는 도구일 뿐이다\"라는 말은 반만 맞다. 어떤 조건에서 어떤 도구를 꺼낼지 판단하는 능력이 디렉터의 실력이다.\n\nSora 종료는 하나의 도구에 의존하던 습관을 점검하는 계기가 됐다. 그리고 그게 나쁘지 않았다.\n\n#AI영상 #미디어아트 #CreativeDirector #생성AI #Runway"
    },
    "carousel": {
      "badge": "AI CREATIVE",
      "cover_bold": "Sora 닫혔다",
      "cover_accent": "Sora 닫혔다",
      "cover_rest": [
        "그래서 디렉터들이 지금 쓰는 4개"
      ],
      "cover_keyword": "지금 쓰는 4개",
      "reel_hook": "Sora 사라진 뒤 바뀐 것",
      "caption": "AI for Creators · parkjunhyuk.xyz",
      "facts": [
        "강점이 겹치는 모델은 없었다",
        "루프 조건이 실력을 가린다",
        "도구 선택이 디렉팅의 일부다"
      ],
      "points": [
        {
          "title": "Sora가 문을 닫은 이유",
          "body": "2026년 4월 Sora가 종료됐다. 데모와 실무 사이의 간격을 끝내 좁히지 못했다.",
          "image_query": "dark monitor screen glowing AI interface studio night",
          "image": "out/daily/0/_pt1.jpg"
        },
        {
          "title": "Veo 3.1의 강점",
          "body": "모션이 자연스럽고 색감이 일관됐다. 파사드 배경처럼 긴 루프에서 안정적이었다.",
          "image_query": "smooth looping light animation on building facade close detail",
          "image": "out/daily/0/_pt2.jpg"
        },
        {
          "title": "Kling 3.0의 강점",
          "body": "프롬프트 반응이 빠르고 구조적인 장면 구성에 강했다. 반면 루프 끝부분이 튀었다.",
          "image_query": "structured motion graphic projection on architecture wall night",
          "image": "out/daily/0/_pt3.jpg"
        },
        {
          "title": "Seedance 2.0의 강점",
          "body": "질감과 색온도 표현이 섬세했다. 분위기 위주의 짧은 루프에 잘 맞았다.",
          "image_query": "warm textured light glowing softly on concrete facade surface",
          "image": "out/daily/0/_pt4.jpg"
        },
        {
          "title": "Runway의 강점",
          "body": "편집 연동이 가장 편했다. 기존 영상 위에 얹는 작업에서 속도가 달랐다.",
          "image_query": "video editing timeline screen with glowing overlay footage studio",
          "image": "out/daily/0/_pt5.jpg"
        }
      ],
      "outro_line": "Sora가 없어도 작업은 계속된다.\n도구보다 판단이 먼저다.",
      "top_image": "out/daily/0/_hero.jpg"
    },
    "topic_meta": {
      "theme": "「창작 노트」 — 일과 창작에 대한 1인칭 에세이·관점. (CRAFT TALK식 에세이)",
      "pillar": "Creative Leadership (팀 운영·PM·디렉팅)",
      "date": "2026-07-18"
    },
    "_type": "carousel",
    "_dir": "0",
    "_slides": [
      "01_cover.jpg",
      "02_point.jpg",
      "03_point.jpg",
      "04_point.jpg",
      "05_point.jpg",
      "06_point.jpg",
      "07_outro.jpg"
    ]
  },
  {
    "topic": "Sound Room — 소리만으로 공간 전체를 바꾸는 몰입형 사운드 전시 구상",
    "image_query": "immersive sound installation dark room ambient light",
    "instagram": {
      "caption": "「창작 노트」\n\n눈을 감으면 공간이 달라진다.\n\n빛도, 스크린도 아니다.\n소리 하나가 방 전체를 뒤집는다.\n\n지금 구상 중인 Sound Room은\n청각만으로 몰입을 만드는 공간이다.\n\n시각 자극이 빠지면 사람은 오히려 더 깊이 반응한다.\n그게 이 작업을 시작한 이유다.\n\n\nClose your eyes. The room changes.\nOnly sound — no screens, no light tricks.\nDesigning an immersive space built entirely on what you hear.\n\n#사운드아트 #몰입형전시 #공간경험 #인터랙티브아트 #미디어아트 #사운드인스톨레이션 #전시기획",
      "series": "1 Minute Media Art"
    },
    "facebook": {
      "text": "「창작 노트」\n\n나는 전시장에서 눈을 감아본 적이 있다.\n\n그 순간 공간이 사라지는 게 아니라, 오히려 더 커졌다.\n벽의 위치가 느껴지고, 공기의 밀도가 달라지고, 어디서 소리가 오는지 몸이 먼저 알아챘다.\n\n우리는 공간을 '보는 것'이라고 너무 당연하게 전제한다.\n그런데 나는 반대로 묻고 싶었다. 소리만 남기면 어떻게 될까.\n\n지금 구상하는 Sound Room은 그 질문에서 출발했다. 시각 자극을 모두 걷어내고, 사운드만으로 공간의 형태와 감각을 바꾸는 몰입형 방이다. Lux Sound Room에서 힌트를 얻었지만, 방향은 다르게 가져가고 싶다.\n\n기술은 단순하다. 복잡한 장비보다, 소리를 어떻게 배치하느냐가 경험을 결정한다.\n관람객이 방에 들어서는 순간 — 무엇을 보기 전에 — 몸이 먼저 반응하는 공간. 그게 목표다.\n\n시각에 의존하지 않는 전시를 만들어본 적 있다면, 그때 관람객이 어떻게 달라지던가요?"
    },
    "linkedin": {
      "text": "「창작 노트」\n\n전시를 기획하면서 한 가지를 배웠다. 자극이 많을수록 사람이 더 깊이 빠져드는 건 아니다.\n\n오히려 반대다.\n\n지금 구상 중인 Sound Room은 시각 자극을 의도적으로 걷어낸 공간이다. 스크린도, 프로젝션도 없다. 소리만 남긴다.\n\n공간 경험 프로젝트를 해오면서 느낀 건, 관람객이 가장 강하게 반응하는 순간이 '가장 화려한 장면'이 아니라는 점이다. 기대와 다른 감각이 들어올 때, 몸이 먼저 반응한다.\n\n눈을 감으면 벽의 위치가 들린다. 소리가 어디서 오는지 몸이 계산한다. 시각이 빠진 자리를 청각과 촉각이 채운다.\n\nSound Room은 그 원리를 공간 단위로 실험하는 작업이다. 기술 구성은 간단하게 가져가려 한다. 복잡한 장비보다 사운드의 배치와 밀도가 경험을 만든다.\n\n\"감각 하나를 뺐을 때 나머지가 열린다.\"\n\n이 작업은 아직 초안 단계다. 하지만 방향은 분명하다. 공간이 보여주는 것보다, 느끼게 하는 것이 더 오래 남는다.\n\n#사운드아트 #몰입형공간 #공간경험 #ImmersiveExhibition #SoundDesign #미디어아트"
    },
    "carousel": {
      "badge": "SOUND SPACE",
      "cover_bold": "소리가 공간을 바꾼다",
      "cover_accent": "공간을 바꾼다",
      "cover_keyword": "눈을 감아라",
      "cover_rest": [
        "시각 없이 만드는 몰입의 조건"
      ],
      "facts": [
        "시각 자극 없이도 몰입은 된다",
        "소리 배치가 공간의 형태를 만든다",
        "몸이 먼저 반응하는 게 진짜 경험"
      ],
      "caption": "1 Minute Media Art · parkjunhyuk.xyz",
      "points": [
        {
          "title": "왜 소리로만 만드나",
          "body": "시각이 없으면 나머지 감각이 열린다. 그 빈자리가 몰입을 만든다.",
          "image_query": "dark empty room with faint ambient glow sound installation"
        },
        {
          "title": "소리로 벽을 만드는 법",
          "body": "소리의 방향과 밀도를 설계하면, 공간의 경계가 들린다.",
          "image_query": "directional speakers installed on dark ceiling immersive room"
        },
        {
          "title": "관람객은 언제 반응하나",
          "body": "화려한 장면보다 기대와 다른 감각이 들어올 때 몸이 먼저 반응한다.",
          "image_query": "person standing alone in dark sound room eyes closed"
        },
        {
          "title": "기술은 단순하게",
          "body": "복잡한 장비보다 소리의 배치가 경험을 결정한다.",
          "image_query": "minimal speaker setup in dark exhibition space ambient light"
        },
        {
          "title": "이 작업이 남기는 것",
          "body": "공간이 보여주는 것보다 느끼게 한 것이 더 오래 기억된다.",
          "image_query": "visitor walking out of immersive dark sound room soft light"
        }
      ],
      "outro_line": "Sound Room은 아직 초안이다.\n하지만 눈을 감았을 때 더 넓어지는 공간을 만들고 싶다는 건 분명하다.",
      "reel_hook": "눈 감으면 공간이 커진다"
    },
    "topic_meta": {
      "theme": "「창작 노트」 — 일과 창작에 대한 1인칭 에세이·관점. (CRAFT TALK식 에세이)",
      "pillar": "Future City (스마트시티·디지털 공공예술·도시 경험)",
      "date": "2026-07-18"
    },
    "_type": "reel",
    "_dir": "reel0",
    "_video": "reel.mp4"
  }
]